{
  "FileVersion": 1,
  "Identifier": "0b33968c-ada5-47b0-9bb5-060fa3b27c77",
  "CreationDate": "2023-10-13T12:17:42.5389576-04:00",
  "LastEdit": "2023-10-13T16:43:10.6670762+00:00",
  "Name": "Zero",
  "Description": "",
  "Tags": [],
  "WriteProtected": false,
  "Equipment": {
    "MainHand": {
      "ItemId": 319962178718461,
      "Stain": 0,
      "Apply": true,
      "ApplyStain": true
    },
    "OffHand": {
      "ItemId": 4294966911,
      "Stain": 0,
      "Apply": true,
      "ApplyStain": true
    },
    "Head": {
      "ItemId": 282578783314958,
      "Stain": 0,
      "Apply": true,
      "ApplyStain": true
    },
    "Body": {
      "ItemId": 283678294942734,
      "Stain": 0,
      "Apply": true,
      "ApplyStain": true
    },
    "Hands": {
      "ItemId": 284777806570510,
      "Stain": 0,
      "Apply": true,
      "ApplyStain": true
    },
    "Legs": {
      "ItemId": 285877318198286,
      "Stain": 0,
      "Apply": true,
      "ApplyStain": true
    },
    "Feet": {
      "ItemId": 286976829826062,
      "Stain": 0,
      "Apply": true,
      "ApplyStain": true
    },
    "Ears": {
      "ItemId": 288076341444752,
      "Stain": 0,
      "Apply": true,
      "ApplyStain": true
    },
    "Neck": {
      "ItemId": 4294967157,
      "Stain": 0,
      "Apply": true,
      "ApplyStain": true
    },
    "Wrists": {
      "ItemId": 4294967156,
      "Stain": 0,
      "Apply": true,
      "ApplyStain": true
    },
    "RFinger": {
      "ItemId": 4294967155,
      "Stain": 0,
      "Apply": true,
      "ApplyStain": true
    },
    "LFinger": {
      "ItemId": 4294967155,
      "Stain": 0,
      "Apply": true,
      "ApplyStain": true
    },
    "Hat": {
      "Show": true,
      "Apply": true
    },
    "Visor": {
      "IsToggled": false,
      "Apply": true
    },
    "Weapon": {
      "Show": true,
      "Apply": true
    }
  },
  "Customize": {
    "ModelId": 0,
    "Race": {
      "Value": 1,
      "Apply": false
    },
    "Gender": {
      "Value": 1,
      "Apply": true
    },
    "BodyType": {
      "Value": 1,
      "Apply": false
    },
    "Height": {
      "Value": 0,
      "Apply": true
    },
    "Clan": {
      "Value": 1,
      "Apply": true
    },
    "Face": {
      "Value": 223,
      "Apply": true
    },
    "Hairstyle": {
      "Value": 219,
      "Apply": true
    },
    "Highlights": {
      "Value": 128,
      "Apply": true
    },
    "SkinColor": {
      "Value": 240,
      "Apply": true
    },
    "EyeColorRight": {
      "Value": 2,
      "Apply": true
    },
    "HairColor": {
      "Value": 23,
      "Apply": true
    },
    "HighlightsColor": {
      "Value": 154,
      "Apply": true
    },
    "FacialFeature1": {
      "Value": 0,
      "Apply": true
    },
    "FacialFeature2": {
      "Value": 0,
      "Apply": true
    },
    "FacialFeature3": {
      "Value": 0,
      "Apply": true
    },
    "FacialFeature4": {
      "Value": 0,
      "Apply": true
    },
    "FacialFeature5": {
      "Value": 0,
      "Apply": true
    },
    "FacialFeature6": {
      "Value": 0,
      "Apply": true
    },
    "FacialFeature7": {
      "Value": 0,
      "Apply": true
    },
    "LegacyTattoo": {
      "Value": 0,
      "Apply": true
    },
    "TattooColor": {
      "Value": 0,
      "Apply": true
    },
    "Eyebrows": {
      "Value": 0,
      "Apply": true
    },
    "EyeColorLeft": {
      "Value": 2,
      "Apply": true
    },
    "EyeShape": {
      "Value": 0,
      "Apply": true
    },
    "SmallIris": {
      "Value": 0,
      "Apply": true
    },
    "Nose": {
      "Value": 0,
      "Apply": true
    },
    "Jaw": {
      "Value": 0,
      "Apply": true
    },
    "Mouth": {
      "Value": 0,
      "Apply": true
    },
    "Lipstick": {
      "Value": 0,
      "Apply": true
    },
    "LipColor": {
      "Value": 0,
      "Apply": true
    },
    "MuscleMass": {
      "Value": 50,
      "Apply": true
    },
    "TailShape": {
      "Value": 0,
      "Apply": false
    },
    "BustSize": {
      "Value": 50,
      "Apply": true
    },
    "FacePaint": {
      "Value": 0,
      "Apply": true
    },
    "FacePaintReversed": {
      "Value": 0,
      "Apply": true
    },
    "FacePaintColor": {
      "Value": 0,
      "Apply": true
    },
    "Wetness": {
      "Value": false,
      "Apply": true
    }
  },
  "Mods": []
}